loyaltytool/__init__.py
loyaltytool/tool.py
loyaltytool-0.0.2.dist-info/LICENSE
loyaltytool-0.0.2.dist-info/METADATA
loyaltytool-0.0.2.dist-info/WHEEL
loyaltytool-0.0.2.dist-info/top_level.txt
loyaltytool-0.0.2.dist-info/RECORD
