Metadata-Version: 2.1
Name: loyaltytool
Version: 0.0.2
Summary: Some simple but useful decorators
Home-page: https://github.com/FQY7
Author: FQY
Author-email: qingyun-feng@qq.com
License: UNKNOWN
Platform: UNKNOWN
Classifier: Programming Language :: Python :: 3
Classifier: License :: OSI Approved :: MIT License
Classifier: Operating System :: OS Independent
License-File: LICENSE
